classifycolors/__init__.py
classifycolors/main.py
classifycolors-0.1.1.dist-info/METADATA
classifycolors-0.1.1.dist-info/WHEEL
classifycolors-0.1.1.dist-info/top_level.txt
classifycolors-0.1.1.dist-info/RECORD
