Metadata-Version: 2.1
Name: classifycolors
Version: 0.1.1
Summary: UNKNOWN
Home-page: UNKNOWN
Author: Elie Fares
License: UNKNOWN
Platform: UNKNOWN
